odoo8_addon_project_description-8.0.1.0.0.99.dev18-py2.7-nspkg.pth
odoo8_addon_project_description-8.0.1.0.0.99.dev18.dist-info/DESCRIPTION.rst
odoo8_addon_project_description-8.0.1.0.0.99.dev18.dist-info/METADATA
odoo8_addon_project_description-8.0.1.0.0.99.dev18.dist-info/RECORD
odoo8_addon_project_description-8.0.1.0.0.99.dev18.dist-info/WHEEL
odoo8_addon_project_description-8.0.1.0.0.99.dev18.dist-info/metadata.json
odoo8_addon_project_description-8.0.1.0.0.99.dev18.dist-info/namespace_packages.txt
odoo8_addon_project_description-8.0.1.0.0.99.dev18.dist-info/top_level.txt
odoo_addons/project_description/README.rst
odoo_addons/project_description/__init__.py
odoo_addons/project_description/__openerp__.py
odoo_addons/project_description/i18n/ar.po
odoo_addons/project_description/i18n/bg.po
odoo_addons/project_description/i18n/bs.po
odoo_addons/project_description/i18n/ca.po
odoo_addons/project_description/i18n/ca_ES.po
odoo_addons/project_description/i18n/cs.po
odoo_addons/project_description/i18n/da.po
odoo_addons/project_description/i18n/de.po
odoo_addons/project_description/i18n/el.po
odoo_addons/project_description/i18n/el_GR.po
odoo_addons/project_description/i18n/en_GB.po
odoo_addons/project_description/i18n/es.po
odoo_addons/project_description/i18n/es_AR.po
odoo_addons/project_description/i18n/es_CL.po
odoo_addons/project_description/i18n/es_CO.po
odoo_addons/project_description/i18n/es_CR.po
odoo_addons/project_description/i18n/es_DO.po
odoo_addons/project_description/i18n/es_EC.po
odoo_addons/project_description/i18n/es_MX.po
odoo_addons/project_description/i18n/es_PE.po
odoo_addons/project_description/i18n/es_PY.po
odoo_addons/project_description/i18n/es_VE.po
odoo_addons/project_description/i18n/et.po
odoo_addons/project_description/i18n/fa.po
odoo_addons/project_description/i18n/fi.po
odoo_addons/project_description/i18n/fr.po
odoo_addons/project_description/i18n/he.po
odoo_addons/project_description/i18n/hr.po
odoo_addons/project_description/i18n/hu.po
odoo_addons/project_description/i18n/id.po
odoo_addons/project_description/i18n/it.po
odoo_addons/project_description/i18n/ja.po
odoo_addons/project_description/i18n/ko.po
odoo_addons/project_description/i18n/lt.po
odoo_addons/project_description/i18n/lv.po
odoo_addons/project_description/i18n/mk.po
odoo_addons/project_description/i18n/mn.po
odoo_addons/project_description/i18n/nb.po
odoo_addons/project_description/i18n/nl_BE.po
